pyitm/__init__.py
pyitm/example_taps.py
pyitm/main.py
pyitm/tcp.py
pyitm/udp.py
pythonitm-0.9.dist-info/LICENSE
pythonitm-0.9.dist-info/WHEEL
pythonitm-0.9.dist-info/METADATA
pythonitm-0.9.dist-info/RECORD
