Metadata-Version: 2.1
Name: pythonitm
Version: 0.9
Summary: An easy to use, TCP and UDP level Man-in-the-middle framework intended for security researchers and practitioners.
Author: Patrick Welzel
Author-email: git@kcirtap.de
Requires-Python: >=3.6
Classifier: License :: OSI Approved :: MIT License
